streamlit_multi_textarea/__init__.py
streamlit_multi_textarea/frontend/build/asset-manifest.json
streamlit_multi_textarea/frontend/build/bootstrap.min.css
streamlit_multi_textarea/frontend/build/index.html
streamlit_multi_textarea/frontend/build/precache-manifest.e83d2a03ff162fe4d5de3403da557fdc.js
streamlit_multi_textarea/frontend/build/service-worker.js
streamlit_multi_textarea/frontend/build/static/js/2.e4606493.chunk.js
streamlit_multi_textarea/frontend/build/static/js/2.e4606493.chunk.js.LICENSE.txt
streamlit_multi_textarea/frontend/build/static/js/2.e4606493.chunk.js.map
streamlit_multi_textarea/frontend/build/static/js/main.e8672309.chunk.js
streamlit_multi_textarea/frontend/build/static/js/main.e8672309.chunk.js.map
streamlit_multi_textarea/frontend/build/static/js/runtime-main.1765f872.js
streamlit_multi_textarea/frontend/build/static/js/runtime-main.1765f872.js.map
streamlit_multi_textarea-0.0.1.dist-info/LICENSE
streamlit_multi_textarea-0.0.1.dist-info/METADATA
streamlit_multi_textarea-0.0.1.dist-info/WHEEL
streamlit_multi_textarea-0.0.1.dist-info/top_level.txt
streamlit_multi_textarea-0.0.1.dist-info/RECORD
