Metadata-Version: 2.1
Name: streamlit-multi-textarea
Version: 0.0.1
Summary: Streamlit componenet can contain multiple text area.
Home-page: UNKNOWN
Author: Planete
Author-email: 
License: UNKNOWN
Platform: UNKNOWN
Requires-Python: >=3.6
License-File: LICENSE
Requires-Dist: streamlit (>=0.63)
